cogents_tools/__init__.py
cogents_tools/groups.py
cogents_tools/py.typed
cogents_tools/agents/askura_agent/README.md
cogents_tools/agents/askura_agent/__init__.py
cogents_tools/agents/askura_agent/askura_agent.py
cogents_tools/agents/askura_agent/conversation.py
cogents_tools/agents/askura_agent/extractor.py
cogents_tools/agents/askura_agent/memory.py
cogents_tools/agents/askura_agent/models.py
cogents_tools/agents/askura_agent/prompts.py
cogents_tools/agents/askura_agent/reflection.py
cogents_tools/agents/askura_agent/summarizer.py
cogents_tools/agents/askura_agent/utils.py
cogents_tools/agents/seekra_agent/README.md
cogents_tools/agents/seekra_agent/__init__.py
cogents_tools/agents/seekra_agent/configuration.py
cogents_tools/agents/seekra_agent/prompts.py
cogents_tools/agents/seekra_agent/researcher.py
cogents_tools/agents/seekra_agent/schemas.py
cogents_tools/agents/seekra_agent/state.py
cogents_tools/integrations/embedgen.py
cogents_tools/integrations/llm.py
cogents_tools/integrations/bu/README.md
cogents_tools/integrations/bu/__init__.py
cogents_tools/integrations/bu/config.py
cogents_tools/integrations/bu/exceptions.py
cogents_tools/integrations/bu/logging_config.py
cogents_tools/integrations/bu/observability.py
cogents_tools/integrations/bu/utils.py
cogents_tools/integrations/bu/agent/gif.py
cogents_tools/integrations/bu/agent/prompts.py
cogents_tools/integrations/bu/agent/service.py
cogents_tools/integrations/bu/agent/system_prompt.md
cogents_tools/integrations/bu/agent/system_prompt_flash.md
cogents_tools/integrations/bu/agent/system_prompt_no_thinking.md
cogents_tools/integrations/bu/agent/views.py
cogents_tools/integrations/bu/agent/message_manager/service.py
cogents_tools/integrations/bu/agent/message_manager/utils.py
cogents_tools/integrations/bu/agent/message_manager/views.py
cogents_tools/integrations/bu/browser/__init__.py
cogents_tools/integrations/bu/browser/events.py
cogents_tools/integrations/bu/browser/profile.py
cogents_tools-0.1.7.dist-info/licenses/LICENSE
cogents_tools-0.1.7.dist-info/METADATA
cogents_tools-0.1.7.dist-info/WHEEL
cogents_tools-0.1.7.dist-info/top_level.txt
cogents_tools-0.1.7.dist-info/RECORD
