Metadata-Version: 2.4
Name: cogents-tools
Version: 0.1.7
Summary: Supportive tools for Cogents, towards a cognitive agentic system
Author-email: Xiaming Chen <chenxm35@gmail.com>
Maintainer-email: Xiaming Chen <chenxm35@gmail.com>
License-Expression: MIT
Project-URL: Homepage, https://github.com/mirasurf/cogents-tools
Project-URL: Repository, https://github.com/mirasurf/cogents-tools
Keywords: agents,multi-agent system,cognition,artificial intelligence
Classifier: Development Status :: 4 - Beta
Classifier: Intended Audience :: Developers
Classifier: Operating System :: OS Independent
Classifier: Programming Language :: Python :: 3
Classifier: Programming Language :: Python :: 3.11
Classifier: Programming Language :: Python :: 3.12
Classifier: Topic :: Software Development :: Libraries :: Python Modules
Requires-Python: >=3.11
License-File: LICENSE
Requires-Dist: cogents-core<0.2.0,>=0.1.9
Requires-Dist: aiohttp>=3.12.15
Requires-Dist: aiofiles>=24.1.0
Requires-Dist: anyio>=4.9.0
Requires-Dist: httpx>=0.28.1
Requires-Dist: psutil>=7.0.0
Requires-Dist: opik>=0.2.0
Requires-Dist: screeninfo>=0.8.1
Requires-Dist: uuid7>=0.1.0
Requires-Dist: authlib>=1.6.0
Requires-Dist: pypdf>=5.7.0
Requires-Dist: cdp-use>=1.4.0
Requires-Dist: markdown-pdf>=1.5
Requires-Dist: html2text>=2025.4.15
Requires-Dist: google-genai<2.0.0,>=1.29.0
Requires-Dist: tavily-python>=0.3.0
Requires-Dist: langchain-tavily>=0.2.11
Requires-Dist: weaviate-client>=4.16.9
Requires-Dist: psycopg2>=2.9.10
Requires-Dist: psycopg2-binary>=2.9.0
Requires-Dist: arxiv>=2.2.0
Requires-Dist: matplotlib>=3.8.0
Requires-Dist: pexpect>=4.9.0
Requires-Dist: ipython>=8.18.0
Requires-Dist: pandas>=2.0.0
Requires-Dist: pillow<12.0,>=10.1.0
Requires-Dist: pymupdf>=1.23.0
Requires-Dist: openpyxl>=3.1.5
Requires-Dist: aliyun-python-sdk-core<3.0.0,>=2.13.1
Requires-Dist: google-api-python-client>=2.174.0
Requires-Dist: google-auth-oauthlib>=1.2.2
Requires-Dist: google-auth>=2.40.3
Requires-Dist: wikipedia-api>=0.6.0
Provides-Extra: dev
Requires-Dist: pytest<9,>=8.2; extra == "dev"
Requires-Dist: pytest-cov>=4.0.0; extra == "dev"
Requires-Dist: pytest-asyncio>=1.1.0; extra == "dev"
Requires-Dist: pytest-tornasync>=0.6.0.post2; extra == "dev"
Requires-Dist: pytest-trio>=0.8.0; extra == "dev"
Requires-Dist: pytest-twisted>=1.14.3; extra == "dev"
Requires-Dist: twisted>=25.5.0; extra == "dev"
Requires-Dist: black>=23.0.0; extra == "dev"
Requires-Dist: isort>=5.12.0; extra == "dev"
Requires-Dist: flake8>=7.3.0; extra == "dev"
Requires-Dist: autoflake>=2.3.1; extra == "dev"
Dynamic: license-file
